{"cameraMode":{"drawMode":0,"name":"Shaded","section":"Shading Mode"},"sceneLighting":true,"audioPlay":false,"sceneViewState":{"m_AlwaysRefresh":false,"showFog":true,"showSkybox":true,"showFlares":true,"showImageEffects":true,"showParticleSystems":true,"showVisualEffectGraphs":true,"m_FxEnabled":true},"in2DMode":false,"pivot":{"x":0.37467846274375918,"y":-0.8883337378501892,"z":5.2404632568359379},"rotation":{"x":-0.06304752826690674,"y":-0.08314153552055359,"z":0.00527155539020896,"w":-0.9945208430290222},"size":10.0,"orthographic":false}